AUTHORS.rst
CHANGES.rst
LICENSE.txt
MANIFEST.in
README.rst
TODO.rst
setup.py
django_html5accordion.egg-info/PKG-INFO
django_html5accordion.egg-info/SOURCES.txt
django_html5accordion.egg-info/dependency_links.txt
django_html5accordion.egg-info/not-zip-safe
django_html5accordion.egg-info/top_level.txt
html5accordion/__init__.py
html5accordion/models.py
html5accordion/static/html5accordion/jquery.html5accordion.js
tests/test.html