Metadata-Version: 1.0
Name: django-html5accordion
Version: 0.1.6
Summary: JS support to expand/collapse content, like HTML5 details/summary elements
Home-page: https://github.com/jgerigmeyer/django-html5accordion/
Author: Jonny Gerig Meyer
Author-email: jonny@oddbird.net
License: UNKNOWN
Platform: UNKNOWN
Classifier: Development Status :: 3 - Alpha
Classifier: Environment :: Web Environment
Classifier: Intended Audience :: Developers
Classifier: License :: OSI Approved :: BSD License
Classifier: Operating System :: OS Independent
Classifier: Framework :: Django
